petbox/dca/__init__.py
petbox/dca/associated.py
petbox/dca/base.py
petbox/dca/bourdet.py
petbox/dca/primary.py
petbox/dca/py.typed
petbox_dca-1.1.1.dist-info/LICENSE
petbox_dca-1.1.1.dist-info/METADATA
petbox_dca-1.1.1.dist-info/WHEEL
petbox_dca-1.1.1.dist-info/top_level.txt
petbox_dca-1.1.1.dist-info/RECORD
