Metadata-Version: 2.1
Name: petbox-dca
Version: 1.1.1
Summary: Decline Curve Library
Home-page: https://github.com/petbox-dev/dca
Author: David S. Fulford
Author-email: petbox-dev@gmail.com
License: MIT
Keywords: petbox-dca,dca,decline curve,type curve,production forecast,production data analysis
Classifier: Development Status :: 5 - Production/Stable
Classifier: Intended Audience :: Science/Research
Classifier: Intended Audience :: Education
Classifier: Intended Audience :: Developers
Classifier: Natural Language :: English
Classifier: License :: OSI Approved :: MIT License
Classifier: Programming Language :: Python :: 3.7
Classifier: Programming Language :: Python :: 3.8
Classifier: Programming Language :: Python :: Implementation :: CPython
Classifier: Topic :: Scientific/Engineering
Classifier: Topic :: Scientific/Engineering :: Mathematics
Classifier: Topic :: Software Development :: Libraries
Classifier: Typing :: Typed
Requires-Python: >=3.7
License-File: LICENSE
Requires-Dist: numpy>=1.21.1
Requires-Dist: scipy>=1.7.1
